{
 "metrics": [
  {
   "measurements": [
    {
     "name": "TotalTime",
     "value": 4669.7767905341316
    },
    {
     "name": "TotalMemoryMigration",
     "value": 33875
    },
    {
     "name": "SumMigrationTime",
     "value": 51127.408294950787
    },
    {
     "name": "TotalSteps",
     "value": 1960
    }
   ]
  },
  {
   "measurements": [
    {
     "name": "TotalTime",
     "value": 4176.5205021219863
    },
    {
     "name": "TotalMemoryMigration",
     "value": 23656
    },
    {
     "name": "SumMigrationTime",
     "value": 35245.005520907223
    },
    {
     "name": "TotalSteps",
     "value": 1467
    }
   ]
  },
  {
   "measurements": [
    {
     "name": "TotalTime",
     "value": 4572.7140518190308
    },
    {
     "name": "TotalMemoryMigration",
     "value": 31598
    },
    {
     "name": "SumMigrationTime",
     "value": 47693.883555241882
    },
    {
     "name": "TotalSteps",
     "value": 1871
    }
   ]
  },
  {
   "measurements": [
    {
     "name": "TotalTime",
     "value": 5501.7339289855054
    },
    {
     "name": "TotalMemoryMigration",
     "value": 26413
    },
    {
     "name": "SumMigrationTime",
     "value": 40072.985903657151
    },
    {
     "name": "TotalSteps",
     "value": 1563
    }
   ]
  },
  {
   "measurements": [
    {
     "name": "TotalTime",
     "value": 3956.609798584107
    },
    {
     "name": "TotalMemoryMigration",
     "value": 26334
    },
    {
     "name": "SumMigrationTime",
     "value": 39796.453445120023
    },
    {
     "name": "TotalSteps",
     "value": 1533
    }
   ]
  },
  {
   "measurements": [
    {
     "name": "TotalTime",
     "value": 4015.295945141911
    },
    {
     "name": "TotalMemoryMigration",
     "value": 23596
    },
    {
     "name": "SumMigrationTime",
     "value": 35286.408488535541
    },
    {
     "name": "TotalSteps",
     "value": 1331
    }
   ]
  },
  {
   "measurements": [
    {
     "name": "TotalTime",
     "value": 3974.7644390509131
    },
    {
     "name": "TotalMemoryMigration",
     "value": 33428
    },
    {
     "name": "SumMigrationTime",
     "value": 50586.533090814926
    },
    {
     "name": "TotalSteps",
     "value": 2032
    }
   ]
  },
  {
   "measurements": [
    {
     "name": "TotalTime",
     "value": 3596.2476616296567
    },
    {
     "name": "TotalMemoryMigration",
     "value": 29172
    },
    {
     "name": "SumMigrationTime",
     "value": 43142.7981088826
    },
    {
     "name": "TotalSteps",
     "value": 1763
    }
   ]
  },
  {
   "measurements": [
    {
     "name": "TotalTime",
     "value": 3285.7069090466903
    },
    {
     "name": "TotalMemoryMigration",
     "value": 22304
    },
    {
     "name": "SumMigrationTime",
     "value": 33530.052148422736
    },
    {
     "name": "TotalSteps",
     "value": 1229
    }
   ]
  },
  {
   "measurements": [
    {
     "name": "TotalTime",
     "value": 4293.3381977375
    },
    {
     "name": "TotalMemoryMigration",
     "value": 29524
    },
    {
     "name": "SumMigrationTime",
     "value": 44072.687721013972
    },
    {
     "name": "TotalSteps",
     "value": 1757
    }
   ]
  },
  {
   "measurements": [
    {
     "name": "TotalTime",
     "value": 5723.4835906497256
    },
    {
     "name": "TotalMemoryMigration",
     "value": 39862
    },
    {
     "name": "SumMigrationTime",
     "value": 60245.705398619561
    },
    {
     "name": "TotalSteps",
     "value": 2186
    }
   ]
  },
  {
   "measurements": [
    {
     "name": "TotalTime",
     "value": 3603.1616996973153
    },
    {
     "name": "TotalMemoryMigration",
     "value": 29196
    },
    {
     "name": "SumMigrationTime",
     "value": 44226.216072089119
    },
    {
     "name": "TotalSteps",
     "value": 1807
    }
   ]
  },
  {
   "measurements": [
    {
     "name": "TotalTime",
     "value": 4520.22272954828
    },
    {
     "name": "TotalMemoryMigration",
     "value": 27580
    },
    {
     "name": "SumMigrationTime",
     "value": 41059.659584145222
    },
    {
     "name": "TotalSteps",
     "value": 1579
    }
   ]
  },
  {
   "measurements": [
    {
     "name": "TotalTime",
     "value": 3987.95279106411
    },
    {
     "name": "TotalMemoryMigration",
     "value": 33180
    },
    {
     "name": "SumMigrationTime",
     "value": 49932.339977285024
    },
    {
     "name": "TotalSteps",
     "value": 1977
    }
   ]
  },
  {
   "measurements": [
    {
     "name": "TotalTime",
     "value": 4302.5224159030131
    },
    {
     "name": "TotalMemoryMigration",
     "value": 36570
    },
    {
     "name": "SumMigrationTime",
     "value": 54529.996810619545
    },
    {
     "name": "TotalSteps",
     "value": 2131
    }
   ]
  },
  {
   "measurements": [
    {
     "name": "TotalTime",
     "value": 3151.2964753796391
    },
    {
     "name": "TotalMemoryMigration",
     "value": 20033
    },
    {
     "name": "SumMigrationTime",
     "value": 29901.238855702777
    },
    {
     "name": "TotalSteps",
     "value": 1243
    }
   ]
  },
  {
   "measurements": [
    {
     "name": "TotalTime",
     "value": 5986.2877122079317
    },
    {
     "name": "TotalMemoryMigration",
     "value": 38773
    },
    {
     "name": "SumMigrationTime",
     "value": 57438.8762089662
    },
    {
     "name": "TotalSteps",
     "value": 2234
    }
   ]
  },
  {
   "measurements": [
    {
     "name": "TotalTime",
     "value": 4438.8282955517025
    },
    {
     "name": "TotalMemoryMigration",
     "value": 36544
    },
    {
     "name": "SumMigrationTime",
     "value": 54599.704850162154
    },
    {
     "name": "TotalSteps",
     "value": 2212
    }
   ]
  },
  {
   "measurements": [
    {
     "name": "TotalTime",
     "value": 5919.2896191519276
    },
    {
     "name": "TotalMemoryMigration",
     "value": 36442
    },
    {
     "name": "SumMigrationTime",
     "value": 54619.354631720445
    },
    {
     "name": "TotalSteps",
     "value": 2093
    }
   ]
  },
  {
   "measurements": [
    {
     "name": "TotalTime",
     "value": 4138.74549883141
    },
    {
     "name": "TotalMemoryMigration",
     "value": 25786
    },
    {
     "name": "SumMigrationTime",
     "value": 38963.720412247065
    },
    {
     "name": "TotalSteps",
     "value": 1493
    }
   ]
  },
  {
   "measurements": [
    {
     "name": "TotalTime",
     "value": 5579.8795212690875
    },
    {
     "name": "TotalMemoryMigration",
     "value": 38603
    },
    {
     "name": "SumMigrationTime",
     "value": 58389.532447729885
    },
    {
     "name": "TotalSteps",
     "value": 2208
    }
   ]
  },
  {
   "measurements": [
    {
     "name": "TotalTime",
     "value": 4651.9240914401807
    },
    {
     "name": "TotalMemoryMigration",
     "value": 27253
    },
    {
     "name": "SumMigrationTime",
     "value": 41051.543834595272
    },
    {
     "name": "TotalSteps",
     "value": 1542
    }
   ]
  },
  {
   "measurements": [
    {
     "name": "TotalTime",
     "value": 4849.3672600910459
    },
    {
     "name": "TotalMemoryMigration",
     "value": 31068
    },
    {
     "name": "SumMigrationTime",
     "value": 47301.400967018133
    },
    {
     "name": "TotalSteps",
     "value": 1882
    }
   ]
  },
  {
   "measurements": [
    {
     "name": "TotalTime",
     "value": 3990.242952220116
    },
    {
     "name": "TotalMemoryMigration",
     "value": 24579
    },
    {
     "name": "SumMigrationTime",
     "value": 36987.716192328575
    },
    {
     "name": "TotalSteps",
     "value": 1320
    }
   ]
  },
  {
   "measurements": [
    {
     "name": "TotalTime",
     "value": 4637.0362753420013
    },
    {
     "name": "TotalMemoryMigration",
     "value": 34339
    },
    {
     "name": "SumMigrationTime",
     "value": 51093.6663820959
    },
    {
     "name": "TotalSteps",
     "value": 2089
    }
   ]
  },
  {
   "measurements": [
    {
     "name": "TotalTime",
     "value": 4256.7598784073034
    },
    {
     "name": "TotalMemoryMigration",
     "value": 25971
    },
    {
     "name": "SumMigrationTime",
     "value": 38574.291011245339
    },
    {
     "name": "TotalSteps",
     "value": 1490
    }
   ]
  },
  {
   "measurements": [
    {
     "name": "TotalTime",
     "value": 4473.2108239691634
    },
    {
     "name": "TotalMemoryMigration",
     "value": 34825
    },
    {
     "name": "SumMigrationTime",
     "value": 52717.746817499195
    },
    {
     "name": "TotalSteps",
     "value": 2023
    }
   ]
  },
  {
   "measurements": [
    {
     "name": "TotalTime",
     "value": 5330.2452885467537
    },
    {
     "name": "TotalMemoryMigration",
     "value": 31444
    },
    {
     "name": "SumMigrationTime",
     "value": 47492.629193829533
    },
    {
     "name": "TotalSteps",
     "value": 1888
    }
   ]
  },
  {
   "measurements": [
    {
     "name": "TotalTime",
     "value": 3806.6748795647227
    },
    {
     "name": "TotalMemoryMigration",
     "value": 28075
    },
    {
     "name": "SumMigrationTime",
     "value": 42076.159062317121
    },
    {
     "name": "TotalSteps",
     "value": 1595
    }
   ]
  },
  {
   "measurements": [
    {
     "name": "TotalTime",
     "value": 6280.034790029551
    },
    {
     "name": "TotalMemoryMigration",
     "value": 38081
    },
    {
     "name": "SumMigrationTime",
     "value": 57662.61679371776
    },
    {
     "name": "TotalSteps",
     "value": 2202
    }
   ]
  },
  {
   "measurements": [
    {
     "name": "TotalTime",
     "value": 4109.9365654361745
    },
    {
     "name": "TotalMemoryMigration",
     "value": 37023
    },
    {
     "name": "SumMigrationTime",
     "value": 55401.516870631247
    },
    {
     "name": "TotalSteps",
     "value": 2174
    }
   ]
  },
  {
   "measurements": [
    {
     "name": "TotalTime",
     "value": 5219.6230368076722
    },
    {
     "name": "TotalMemoryMigration",
     "value": 28758
    },
    {
     "name": "SumMigrationTime",
     "value": 42992.638860792838
    },
    {
     "name": "TotalSteps",
     "value": 1687
    }
   ]
  },
  {
   "measurements": [
    {
     "name": "TotalTime",
     "value": 3401.8263655319465
    },
    {
     "name": "TotalMemoryMigration",
     "value": 19355
    },
    {
     "name": "SumMigrationTime",
     "value": 29132.430245946012
    },
    {
     "name": "TotalSteps",
     "value": 1256
    }
   ]
  },
  {
   "measurements": [
    {
     "name": "TotalTime",
     "value": 3705.0849577605536
    },
    {
     "name": "TotalMemoryMigration",
     "value": 22750
    },
    {
     "name": "SumMigrationTime",
     "value": 34009.218986667387
    },
    {
     "name": "TotalSteps",
     "value": 1315
    }
   ]
  },
  {
   "measurements": [
    {
     "name": "TotalTime",
     "value": 3750.6936524757366
    },
    {
     "name": "TotalMemoryMigration",
     "value": 32537
    },
    {
     "name": "SumMigrationTime",
     "value": 48862.654031831538
    },
    {
     "name": "TotalSteps",
     "value": 1860
    }
   ]
  },
  {
   "measurements": [
    {
     "name": "TotalTime",
     "value": 3511.9679317225628
    },
    {
     "name": "TotalMemoryMigration",
     "value": 27061
    },
    {
     "name": "SumMigrationTime",
     "value": 40826.694595787128
    },
    {
     "name": "TotalSteps",
     "value": 1527
    }
   ]
  },
  {
   "measurements": [
    {
     "name": "TotalTime",
     "value": 4599.9832373176941
    },
    {
     "name": "TotalMemoryMigration",
     "value": 29365
    },
    {
     "name": "SumMigrationTime",
     "value": 43642.449521580449
    },
    {
     "name": "TotalSteps",
     "value": 1681
    }
   ]
  },
  {
   "measurements": [
    {
     "name": "TotalTime",
     "value": 4416.3822567027746
    },
    {
     "name": "TotalMemoryMigration",
     "value": 37883
    },
    {
     "name": "SumMigrationTime",
     "value": 56700.9754419302
    },
    {
     "name": "TotalSteps",
     "value": 2172
    }
   ]
  },
  {
   "measurements": [
    {
     "name": "TotalTime",
     "value": 4288.3297050797737
    },
    {
     "name": "TotalMemoryMigration",
     "value": 21495
    },
    {
     "name": "SumMigrationTime",
     "value": 32120.201959822778
    },
    {
     "name": "TotalSteps",
     "value": 1234
    }
   ]
  },
  {
   "measurements": [
    {
     "name": "TotalTime",
     "value": 3701.0282333666778
    },
    {
     "name": "TotalMemoryMigration",
     "value": 28871
    },
    {
     "name": "SumMigrationTime",
     "value": 42897.452593951355
    },
    {
     "name": "TotalSteps",
     "value": 1701
    }
   ]
  },
  {
   "measurements": [
    {
     "name": "TotalTime",
     "value": 3648.6781773139478
    },
    {
     "name": "TotalMemoryMigration",
     "value": 22186
    },
    {
     "name": "SumMigrationTime",
     "value": 33196.508127841189
    },
    {
     "name": "TotalSteps",
     "value": 1369
    }
   ]
  },
  {
   "measurements": [
    {
     "name": "TotalTime",
     "value": 3321.5889133336332
    },
    {
     "name": "TotalMemoryMigration",
     "value": 22119
    },
    {
     "name": "SumMigrationTime",
     "value": 32598.21105279553
    },
    {
     "name": "TotalSteps",
     "value": 1305
    }
   ]
  },
  {
   "measurements": [
    {
     "name": "TotalTime",
     "value": 5099.5640987906036
    },
    {
     "name": "TotalMemoryMigration",
     "value": 37908
    },
    {
     "name": "SumMigrationTime",
     "value": 56698.92385437795
    },
    {
     "name": "TotalSteps",
     "value": 2157
    }
   ]
  },
  {
   "measurements": [
    {
     "name": "TotalTime",
     "value": 4308.6334511184132
    },
    {
     "name": "TotalMemoryMigration",
     "value": 29504
    },
    {
     "name": "SumMigrationTime",
     "value": 44243.1950577716
    },
    {
     "name": "TotalSteps",
     "value": 1732
    }
   ]
  },
  {
   "measurements": [
    {
     "name": "TotalTime",
     "value": 3795.175473353795
    },
    {
     "name": "TotalMemoryMigration",
     "value": 23019
    },
    {
     "name": "SumMigrationTime",
     "value": 34549.030711555111
    },
    {
     "name": "TotalSteps",
     "value": 1248
    }
   ]
  },
  {
   "measurements": [
    {
     "name": "TotalTime",
     "value": 3446.8540133533284
    },
    {
     "name": "TotalMemoryMigration",
     "value": 19976
    },
    {
     "name": "SumMigrationTime",
     "value": 30631.436644633057
    },
    {
     "name": "TotalSteps",
     "value": 1159
    }
   ]
  },
  {
   "measurements": [
    {
     "name": "TotalTime",
     "value": 4324.2840370743234
    },
    {
     "name": "TotalMemoryMigration",
     "value": 30432
    },
    {
     "name": "SumMigrationTime",
     "value": 46177.9568913733
    },
    {
     "name": "TotalSteps",
     "value": 1780
    }
   ]
  },
  {
   "measurements": [
    {
     "name": "TotalTime",
     "value": 4610.09944494336
    },
    {
     "name": "TotalMemoryMigration",
     "value": 36301
    },
    {
     "name": "SumMigrationTime",
     "value": 54220.0320600478
    },
    {
     "name": "TotalSteps",
     "value": 2107
    }
   ]
  },
  {
   "measurements": [
    {
     "name": "TotalTime",
     "value": 4167.6490845893422
    },
    {
     "name": "TotalMemoryMigration",
     "value": 24006
    },
    {
     "name": "SumMigrationTime",
     "value": 36486.00626955348
    },
    {
     "name": "TotalSteps",
     "value": 1435
    }
   ]
  },
  {
   "measurements": [
    {
     "name": "TotalTime",
     "value": 3881.9756772681271
    },
    {
     "name": "TotalMemoryMigration",
     "value": 20113
    },
    {
     "name": "SumMigrationTime",
     "value": 30319.8656075631
    },
    {
     "name": "TotalSteps",
     "value": 1165
    }
   ]
  },
  {
   "measurements": [
    {
     "name": "TotalTime",
     "value": 3922.1584315751979
    },
    {
     "name": "TotalMemoryMigration",
     "value": 37046
    },
    {
     "name": "SumMigrationTime",
     "value": 55402.364043226764
    },
    {
     "name": "TotalSteps",
     "value": 2173
    }
   ]
  },
  {
   "measurements": [
    {
     "name": "TotalTime",
     "value": 3981.0261801139836
    },
    {
     "name": "TotalMemoryMigration",
     "value": 23374
    },
    {
     "name": "SumMigrationTime",
     "value": 35041.743731377748
    },
    {
     "name": "TotalSteps",
     "value": 1353
    }
   ]
  },
  {
   "measurements": [
    {
     "name": "TotalTime",
     "value": 4030.3509651261384
    },
    {
     "name": "TotalMemoryMigration",
     "value": 33801
    },
    {
     "name": "SumMigrationTime",
     "value": 50745.092571491092
    },
    {
     "name": "TotalSteps",
     "value": 2153
    }
   ]
  },
  {
   "measurements": [
    {
     "name": "TotalTime",
     "value": 3584.132958390438
    },
    {
     "name": "TotalMemoryMigration",
     "value": 29754
    },
    {
     "name": "SumMigrationTime",
     "value": 44584.447559673928
    },
    {
     "name": "TotalSteps",
     "value": 1792
    }
   ]
  },
  {
   "measurements": [
    {
     "name": "TotalTime",
     "value": 4444.1525359060633
    },
    {
     "name": "TotalMemoryMigration",
     "value": 31270
    },
    {
     "name": "SumMigrationTime",
     "value": 47149.153190521822
    },
    {
     "name": "TotalSteps",
     "value": 1831
    }
   ]
  },
  {
   "measurements": [
    {
     "name": "TotalTime",
     "value": 5369.8004203083456
    },
    {
     "name": "TotalMemoryMigration",
     "value": 36946
    },
    {
     "name": "SumMigrationTime",
     "value": 55735.868014379477
    },
    {
     "name": "TotalSteps",
     "value": 2190
    }
   ]
  },
  {
   "measurements": [
    {
     "name": "TotalTime",
     "value": 5288.2933967645786
    },
    {
     "name": "TotalMemoryMigration",
     "value": 36969
    },
    {
     "name": "SumMigrationTime",
     "value": 55452.476020302573
    },
    {
     "name": "TotalSteps",
     "value": 2109
    }
   ]
  },
  {
   "measurements": [
    {
     "name": "TotalTime",
     "value": 5070.9761571275767
    },
    {
     "name": "TotalMemoryMigration",
     "value": 33408
    },
    {
     "name": "SumMigrationTime",
     "value": 50458.163860612978
    },
    {
     "name": "TotalSteps",
     "value": 1910
    }
   ]
  },
  {
   "measurements": [
    {
     "name": "TotalTime",
     "value": 4302.5889590819716
    },
    {
     "name": "TotalMemoryMigration",
     "value": 21747
    },
    {
     "name": "SumMigrationTime",
     "value": 33007.244894546508
    },
    {
     "name": "TotalSteps",
     "value": 1290
    }
   ]
  },
  {
   "measurements": [
    {
     "name": "TotalTime",
     "value": 4443.0392253573518
    },
    {
     "name": "TotalMemoryMigration",
     "value": 34340
    },
    {
     "name": "SumMigrationTime",
     "value": 51383.541933046625
    },
    {
     "name": "TotalSteps",
     "value": 1962
    }
   ]
  },
  {
   "measurements": [
    {
     "name": "TotalTime",
     "value": 5012.6030462510744
    },
    {
     "name": "TotalMemoryMigration",
     "value": 28228
    },
    {
     "name": "SumMigrationTime",
     "value": 42246.284900932034
    },
    {
     "name": "TotalSteps",
     "value": 1612
    }
   ]
  },
  {
   "measurements": [
    {
     "name": "TotalTime",
     "value": 4296.1921447409632
    },
    {
     "name": "TotalMemoryMigration",
     "value": 22756
    },
    {
     "name": "SumMigrationTime",
     "value": 34171.724723551204
    },
    {
     "name": "TotalSteps",
     "value": 1369
    }
   ]
  },
  {
   "measurements": [
    {
     "name": "TotalTime",
     "value": 3358.1147288672969
    },
    {
     "name": "TotalMemoryMigration",
     "value": 27015
    },
    {
     "name": "SumMigrationTime",
     "value": 40680.763148085745
    },
    {
     "name": "TotalSteps",
     "value": 1705
    }
   ]
  },
  {
   "measurements": [
    {
     "name": "TotalTime",
     "value": 4824.7179166943279
    },
    {
     "name": "TotalMemoryMigration",
     "value": 36163
    },
    {
     "name": "SumMigrationTime",
     "value": 53494.6359433562
    },
    {
     "name": "TotalSteps",
     "value": 2128
    }
   ]
  },
  {
   "measurements": [
    {
     "name": "TotalTime",
     "value": 4415.4492952797691
    },
    {
     "name": "TotalMemoryMigration",
     "value": 38156
    },
    {
     "name": "SumMigrationTime",
     "value": 57206.457995633042
    },
    {
     "name": "TotalSteps",
     "value": 2196
    }
   ]
  },
  {
   "measurements": [
    {
     "name": "TotalTime",
     "value": 5163.9989586060956
    },
    {
     "name": "TotalMemoryMigration",
     "value": 31011
    },
    {
     "name": "SumMigrationTime",
     "value": 46221.462513668048
    },
    {
     "name": "TotalSteps",
     "value": 1996
    }
   ]
  },
  {
   "measurements": [
    {
     "name": "TotalTime",
     "value": 5186.2381375296054
    },
    {
     "name": "TotalMemoryMigration",
     "value": 27549
    },
    {
     "name": "SumMigrationTime",
     "value": 41694.396912728007
    },
    {
     "name": "TotalSteps",
     "value": 1540
    }
   ]
  },
  {
   "measurements": [
    {
     "name": "TotalTime",
     "value": 3978.5050182615687
    },
    {
     "name": "TotalMemoryMigration",
     "value": 22872
    },
    {
     "name": "SumMigrationTime",
     "value": 33865.02829433063
    },
    {
     "name": "TotalSteps",
     "value": 1352
    }
   ]
  },
  {
   "measurements": [
    {
     "name": "TotalTime",
     "value": 4045.3665302344466
    },
    {
     "name": "TotalMemoryMigration",
     "value": 21559
    },
    {
     "name": "SumMigrationTime",
     "value": 32215.361752477555
    },
    {
     "name": "TotalSteps",
     "value": 1128
    }
   ]
  },
  {
   "measurements": [
    {
     "name": "TotalTime",
     "value": 5048.36114388117
    },
    {
     "name": "TotalMemoryMigration",
     "value": 30068
    },
    {
     "name": "SumMigrationTime",
     "value": 44752.501473355616
    },
    {
     "name": "TotalSteps",
     "value": 1654
    }
   ]
  },
  {
   "measurements": [
    {
     "name": "TotalTime",
     "value": 4521.3114535150262
    },
    {
     "name": "TotalMemoryMigration",
     "value": 24572
    },
    {
     "name": "SumMigrationTime",
     "value": 37046.00009112151
    },
    {
     "name": "TotalSteps",
     "value": 1472
    }
   ]
  },
  {
   "measurements": [
    {
     "name": "TotalTime",
     "value": 3975.919975558124
    },
    {
     "name": "TotalMemoryMigration",
     "value": 19898
    },
    {
     "name": "SumMigrationTime",
     "value": 30073.082709130576
    },
    {
     "name": "TotalSteps",
     "value": 1141
    }
   ]
  },
  {
   "measurements": [
    {
     "name": "TotalTime",
     "value": 6714.5704359202127
    },
    {
     "name": "TotalMemoryMigration",
     "value": 25721
    },
    {
     "name": "SumMigrationTime",
     "value": 38796.157720821728
    },
    {
     "name": "TotalSteps",
     "value": 1353
    }
   ]
  },
  {
   "measurements": [
    {
     "name": "TotalTime",
     "value": 3291.6294917728455
    },
    {
     "name": "TotalMemoryMigration",
     "value": 26936
    },
    {
     "name": "SumMigrationTime",
     "value": 40213.80298078974
    },
    {
     "name": "TotalSteps",
     "value": 1541
    }
   ]
  },
  {
   "measurements": [
    {
     "name": "TotalTime",
     "value": 4900.941045334539
    },
    {
     "name": "TotalMemoryMigration",
     "value": 29594
    },
    {
     "name": "SumMigrationTime",
     "value": 44825.381511416126
    },
    {
     "name": "TotalSteps",
     "value": 1775
    }
   ]
  },
  {
   "measurements": [
    {
     "name": "TotalTime",
     "value": 4029.4049947128533
    },
    {
     "name": "TotalMemoryMigration",
     "value": 26119
    },
    {
     "name": "SumMigrationTime",
     "value": 38890.770174529687
    },
    {
     "name": "TotalSteps",
     "value": 1468
    }
   ]
  },
  {
   "measurements": [
    {
     "name": "TotalTime",
     "value": 3292.7621551538959
    },
    {
     "name": "TotalMemoryMigration",
     "value": 26773
    },
    {
     "name": "SumMigrationTime",
     "value": 40200.739203825724
    },
    {
     "name": "TotalSteps",
     "value": 1584
    }
   ]
  },
  {
   "measurements": [
    {
     "name": "TotalTime",
     "value": 4424.3149575543976
    },
    {
     "name": "TotalMemoryMigration",
     "value": 34236
    },
    {
     "name": "SumMigrationTime",
     "value": 51071.656998041552
    },
    {
     "name": "TotalSteps",
     "value": 1941
    }
   ]
  },
  {
   "measurements": [
    {
     "name": "TotalTime",
     "value": 4874.1534455854862
    },
    {
     "name": "TotalMemoryMigration",
     "value": 30914
    },
    {
     "name": "SumMigrationTime",
     "value": 45653.947436752263
    },
    {
     "name": "TotalSteps",
     "value": 1817
    }
   ]
  },
  {
   "measurements": [
    {
     "name": "TotalTime",
     "value": 3854.0654335583063
    },
    {
     "name": "TotalMemoryMigration",
     "value": 24301
    },
    {
     "name": "SumMigrationTime",
     "value": 35951.239469249173
    },
    {
     "name": "TotalSteps",
     "value": 1446
    }
   ]
  },
  {
   "measurements": [
    {
     "name": "TotalTime",
     "value": 3576.5296871551759
    },
    {
     "name": "TotalMemoryMigration",
     "value": 20366
    },
    {
     "name": "SumMigrationTime",
     "value": 30902.198563806203
    },
    {
     "name": "TotalSteps",
     "value": 1214
    }
   ]
  },
  {
   "measurements": [
    {
     "name": "TotalTime",
     "value": 4160.3775065178443
    },
    {
     "name": "TotalMemoryMigration",
     "value": 28049
    },
    {
     "name": "SumMigrationTime",
     "value": 42010.397379565678
    },
    {
     "name": "TotalSteps",
     "value": 1581
    }
   ]
  },
  {
   "measurements": [
    {
     "name": "TotalTime",
     "value": 5385.9091988661085
    },
    {
     "name": "TotalMemoryMigration",
     "value": 20691
    },
    {
     "name": "SumMigrationTime",
     "value": 31363.415066434522
    },
    {
     "name": "TotalSteps",
     "value": 1126
    }
   ]
  },
  {
   "measurements": [
    {
     "name": "TotalTime",
     "value": 4395.2106715095924
    },
    {
     "name": "TotalMemoryMigration",
     "value": 23541
    },
    {
     "name": "SumMigrationTime",
     "value": 34849.614192682769
    },
    {
     "name": "TotalSteps",
     "value": 1455
    }
   ]
  },
  {
   "measurements": [
    {
     "name": "TotalTime",
     "value": 4193.7882397237172
    },
    {
     "name": "TotalMemoryMigration",
     "value": 24246
    },
    {
     "name": "SumMigrationTime",
     "value": 36329.007432592109
    },
    {
     "name": "TotalSteps",
     "value": 1405
    }
   ]
  },
  {
   "measurements": [
    {
     "name": "TotalTime",
     "value": 3896.841588673326
    },
    {
     "name": "TotalMemoryMigration",
     "value": 34498
    },
    {
     "name": "SumMigrationTime",
     "value": 52263.959602035604
    },
    {
     "name": "TotalSteps",
     "value": 2171
    }
   ]
  },
  {
   "measurements": [
    {
     "name": "TotalTime",
     "value": 4702.4381280641974
    },
    {
     "name": "TotalMemoryMigration",
     "value": 34128
    },
    {
     "name": "SumMigrationTime",
     "value": 51464.71329437392
    },
    {
     "name": "TotalSteps",
     "value": 1974
    }
   ]
  },
  {
   "measurements": [
    {
     "name": "TotalTime",
     "value": 4536.8379297487782
    },
    {
     "name": "TotalMemoryMigration",
     "value": 35202
    },
    {
     "name": "SumMigrationTime",
     "value": 52516.343788160913
    },
    {
     "name": "TotalSteps",
     "value": 2093
    }
   ]
  },
  {
   "measurements": [
    {
     "name": "TotalTime",
     "value": 4321.3836114902942
    },
    {
     "name": "TotalMemoryMigration",
     "value": 26368
    },
    {
     "name": "SumMigrationTime",
     "value": 39915.303050139839
    },
    {
     "name": "TotalSteps",
     "value": 1581
    }
   ]
  },
  {
   "measurements": [
    {
     "name": "TotalTime",
     "value": 4286.3943296683456
    },
    {
     "name": "TotalMemoryMigration",
     "value": 37277
    },
    {
     "name": "SumMigrationTime",
     "value": 55092.906827239225
    },
    {
     "name": "TotalSteps",
     "value": 2181
    }
   ]
  },
  {
   "measurements": [
    {
     "name": "TotalTime",
     "value": 4957.9257992215025
    },
    {
     "name": "TotalMemoryMigration",
     "value": 27713
    },
    {
     "name": "SumMigrationTime",
     "value": 41377.347794296329
    },
    {
     "name": "TotalSteps",
     "value": 1570
    }
   ]
  },
  {
   "measurements": [
    {
     "name": "TotalTime",
     "value": 3226.4561491743925
    },
    {
     "name": "TotalMemoryMigration",
     "value": 19686
    },
    {
     "name": "SumMigrationTime",
     "value": 29465.834773921179
    },
    {
     "name": "TotalSteps",
     "value": 1191
    }
   ]
  },
  {
   "measurements": [
    {
     "name": "TotalTime",
     "value": 3878.7625177477848
    },
    {
     "name": "TotalMemoryMigration",
     "value": 20167
    },
    {
     "name": "SumMigrationTime",
     "value": 29925.079584358904
    },
    {
     "name": "TotalSteps",
     "value": 1156
    }
   ]
  },
  {
   "measurements": [
    {
     "name": "TotalTime",
     "value": 4972.9704869846109
    },
    {
     "name": "TotalMemoryMigration",
     "value": 37093
    },
    {
     "name": "SumMigrationTime",
     "value": 55575.601341159607
    },
    {
     "name": "TotalSteps",
     "value": 2181
    }
   ]
  },
  {
   "measurements": [
    {
     "name": "TotalTime",
     "value": 3987.309364953901
    },
    {
     "name": "TotalMemoryMigration",
     "value": 27738
    },
    {
     "name": "SumMigrationTime",
     "value": 41488.954688044163
    },
    {
     "name": "TotalSteps",
     "value": 1604
    }
   ]
  },
  {
   "measurements": [
    {
     "name": "TotalTime",
     "value": 4297.6598166083168
    },
    {
     "name": "TotalMemoryMigration",
     "value": 28749
    },
    {
     "name": "SumMigrationTime",
     "value": 43447.619115245587
    },
    {
     "name": "TotalSteps",
     "value": 1634
    }
   ]
  },
  {
   "measurements": [
    {
     "name": "TotalTime",
     "value": 4612.73056684298
    },
    {
     "name": "TotalMemoryMigration",
     "value": 29651
    },
    {
     "name": "SumMigrationTime",
     "value": 44508.512534870541
    },
    {
     "name": "TotalSteps",
     "value": 1786
    }
   ]
  },
  {
   "measurements": [
    {
     "name": "TotalTime",
     "value": 4465.8122245397917
    },
    {
     "name": "TotalMemoryMigration",
     "value": 34341
    },
    {
     "name": "SumMigrationTime",
     "value": 51638.619466132332
    },
    {
     "name": "TotalSteps",
     "value": 1988
    }
   ]
  },
  {
   "measurements": [
    {
     "name": "TotalTime",
     "value": 4297.0017631540559
    },
    {
     "name": "TotalMemoryMigration",
     "value": 27360
    },
    {
     "name": "SumMigrationTime",
     "value": 41157.18105487198
    },
    {
     "name": "TotalSteps",
     "value": 1578
    }
   ]
  },
  {
   "measurements": [
    {
     "name": "TotalTime",
     "value": 4794.8387722669459
    },
    {
     "name": "TotalMemoryMigration",
     "value": 37433
    },
    {
     "name": "SumMigrationTime",
     "value": 56804.251263960374
    },
    {
     "name": "TotalSteps",
     "value": 2156
    }
   ]
  }
 ],
 "tests": 100,
 "solved": 100
}
